<?xml version="1.0" encoding="utf-8" ?>
<dwsync>
<file name="nextgen-icons.ttf" server="10.1.1.200/../../var/www/web/" local="133307555650000000" remote="133307555650000000" Dst="0" />
<file name="fa-brands-400.ttf" server="10.1.1.200/../../var/www/web/" local="133307555650000000" remote="133307555650000000" Dst="0" />
<file name="fa-light-300.ttf" server="10.1.1.200/../../var/www/web/" local="133307555650000000" remote="133307555650000000" Dst="0" />
<file name="fa-solid-900.woff" server="10.1.1.200/../../var/www/web/" local="133307555650000000" remote="133307555650000000" Dst="0" />
<file name="fa-regular-400.woff" server="10.1.1.200/../../var/www/web/" local="133307555650000000" remote="133307555650000000" Dst="0" />
<file name="fa-light-300.svg" server="10.1.1.200/../../var/www/web/" local="133307555650000000" remote="133307555650000000" Dst="0" />
<file name="nextgen-icons.woff" server="10.1.1.200/../../var/www/web/" local="133307555650000000" remote="133307555650000000" Dst="0" />
<file name="fa-regular-400.ttf" server="10.1.1.200/../../var/www/web/" local="133307555650000000" remote="133307555650000000" Dst="0" />
<file name="fa-solid-900.woff2" server="10.1.1.200/../../var/www/web/" local="133307555650000000" remote="133307555650000000" Dst="0" />
<file name="nextgen-icons.woff2" server="10.1.1.200/../../var/www/web/" local="133307555650000000" remote="133307555650000000" Dst="0" />
<file name="fa-solid-900.ttf" server="10.1.1.200/../../var/www/web/" local="133307555650000000" remote="133307555650000000" Dst="0" />
<file name="fa-light-300.eot" server="10.1.1.200/../../var/www/web/" local="133307555650000000" remote="133307555650000000" Dst="0" />
<file name="fa-brands-400.svg" server="10.1.1.200/../../var/www/web/" local="133307555650000000" remote="133307555650000000" Dst="0" />
<file name="nextgen-icons.eot" server="10.1.1.200/../../var/www/web/" local="133307555650000000" remote="133307555650000000" Dst="0" />
<file name="fa-solid-900.eot" server="10.1.1.200/../../var/www/web/" local="133307555650000000" remote="133307555650000000" Dst="0" />
<file name="fa-brands-400.woff2" server="10.1.1.200/../../var/www/web/" local="133307555650000000" remote="133307555650000000" Dst="0" />
<file name="fa-brands-400.eot" server="10.1.1.200/../../var/www/web/" local="133307555650000000" remote="133307555650000000" Dst="0" />
<file name="fa-regular-400.svg" server="10.1.1.200/../../var/www/web/" local="133307555650000000" remote="133307555650000000" Dst="0" />
<file name="fa-regular-400.eot" server="10.1.1.200/../../var/www/web/" local="133307555650000000" remote="133307555650000000" Dst="0" />
<file name="fa-brands-400.woff" server="10.1.1.200/../../var/www/web/" local="133307555650000000" remote="133307555650000000" Dst="0" />
<file name="fa-light-300.woff2" server="10.1.1.200/../../var/www/web/" local="133307555650000000" remote="133307555650000000" Dst="0" />
<file name="fa-solid-900.svg" server="10.1.1.200/../../var/www/web/" local="133307555650000000" remote="133307555650000000" Dst="0" />
<file name="summernote.eot" server="10.1.1.200/../../var/www/web/" local="133307555650000000" remote="133307555650000000" Dst="0" />
<file name="nextgen-icons.svg" server="10.1.1.200/../../var/www/web/" local="133307555650000000" remote="133307555650000000" Dst="0" />
<file name="fa-light-300.woff" server="10.1.1.200/../../var/www/web/" local="133307555650000000" remote="133307555650000000" Dst="0" />
<file name="summernote.ttf" server="10.1.1.200/../../var/www/web/" local="133307555650000000" remote="133307555650000000" Dst="0" />
<file name="fa-regular-400.woff2" server="10.1.1.200/../../var/www/web/" local="133307555650000000" remote="133307555650000000" Dst="0" />
<file name="summernote.woff" server="10.1.1.200/../../var/www/web/" local="133307555660000000" remote="133307555660000000" Dst="0" />
</dwsync>