<?xml version="1.0" encoding="utf-8" ?>
<dwsync>
<file name="_log.php" server="10.1.1.200/../../var/www/web/" local="133323081550000000" remote="133323081550000000" Dst="0" />
<file name="_page-footer.php" server="10.1.1.200/../../var/www/web/" local="133307555340000000" remote="133307555340000000" Dst="0" />
<file name="_panel-hdr.php" server="10.1.1.200/../../var/www/web/" local="133307555340000000" remote="133307555340000000" Dst="0" />
<file name="_out.php" server="10.1.1.200/../../var/www/web/" local="133349832770000000" remote="133349832770000000" Dst="0" />
<file name="_page-header.php" server="10.1.1.200/../../var/www/web/" local="133349831920000000" remote="133349831920000000" Dst="0" />
<file name="_captcha.php" server="10.1.1.200/../../var/www/web/" local="133307555340000000" remote="133307555340000000" Dst="0" />
<file name="_page-setting.php" server="10.1.1.200/../../var/www/web/" local="133307555340000000" remote="133307555340000000" Dst="0" />
<file name="_Aside.php" server="10.1.1.200/../../var/www/web/" local="133530726290000000" remote="133530726290000000" Dst="0" />
<file name="_breadcrumb.php" server="10.1.1.200/../../var/www/web/" local="133307555340000000" remote="133307555340000000" Dst="0" />
</dwsync>